setup.py
bovespa/__init__.py
bovespa/file.py
bovespa/record.py
bovespa.egg-info/PKG-INFO
bovespa.egg-info/SOURCES.txt
bovespa.egg-info/dependency_links.txt
bovespa.egg-info/not-zip-safe
bovespa.egg-info/top_level.txt
bovespa/utils/__init__.py
bovespa/utils/content.py
bovespa/utils/layout.py