Metadata-Version: 1.0
Name: bovespa
Version: 0.1.0
Summary: reads bovespa historic quote files
Home-page: http://github.com/thypad/bovespa
Author: Thyago Neves Porpino
Author-email: thyago.porpino@gmail.com
License: MIT
Platform: UNKNOWN
